upyble/SI_units.csv
upyble/SI_units.py
upyble/__init__.py
upyble/appearances.py
upyble/chars.py
upyble/descriptors.py
upyble/get_chars_xml.py
upyble/get_descriptors_xml.py
upyble/manufacturer.csv
upyble/manufacturer.py
upyble/servs.py
upyble/style_customs.py
upyble/upybledevice.py
upyble/chars_xml/aerobic_heart_rate_lower_limit.xml
upyble/chars_xml/aerobic_heart_rate_upper_limit.xml
upyble/chars_xml/aerobic_threshold.xml
upyble/chars_xml/age.xml
upyble/chars_xml/aggregate.xml
upyble/chars_xml/alert_category_id.xml
upyble/chars_xml/alert_category_id_bit_mask.xml
upyble/chars_xml/alert_level.xml
upyble/chars_xml/alert_notification_control_point.xml
upyble/chars_xml/alert_status.xml
upyble/chars_xml/altitude.xml
upyble/chars_xml/anaerobic_heart_rate_lower_limit.xml
upyble/chars_xml/anaerobic_heart_rate_upper_limit.xml
upyble/chars_xml/anaerobic_threshold.xml
upyble/chars_xml/analog.xml
upyble/chars_xml/analog_output.xml
upyble/chars_xml/apparent_wind_direction.xml
upyble/chars_xml/apparent_wind_speed.xml
upyble/chars_xml/appearance.xml
upyble/chars_xml/barometric_pressure_trend.xml
upyble/chars_xml/battery_level.xml
upyble/chars_xml/battery_level_state.xml
upyble/chars_xml/battery_power_state.xml
upyble/chars_xml/blood_pressure_feature.xml
upyble/chars_xml/blood_pressure_measurement.xml
upyble/chars_xml/body_composition_feature.xml
upyble/chars_xml/body_composition_measurement.xml
upyble/chars_xml/body_sensor_location.xml
upyble/chars_xml/bond_management_control_point.xml
upyble/chars_xml/bond_management_features.xml
upyble/chars_xml/boot_keyboard_input_report.xml
upyble/chars_xml/boot_keyboard_output_report.xml
upyble/chars_xml/boot_mouse_input_report.xml
upyble/chars_xml/bss_control_point.xml
upyble/chars_xml/bss_response.xml
upyble/chars_xml/central_address_resolution.xml
upyble/chars_xml/cgm_feature.xml
upyble/chars_xml/cgm_measurement.xml
upyble/chars_xml/cgm_session_run_time.xml
upyble/chars_xml/cgm_session_start_time.xml
upyble-0.0.3.dist-info/LICENSE
upyble-0.0.3.dist-info/METADATA
upyble-0.0.3.dist-info/WHEEL
upyble-0.0.3.dist-info/top_level.txt
upyble-0.0.3.dist-info/RECORD
