Metadata-Version: 2.1
Name: upyble
Version: 0.0.3
Summary: Command line tool for Bluetooth Low Energy MicroPython devices
Home-page: http://github.com/Carglglz/upyble
Author: Carlos Gil Gonzalez
Author-email: carlosgilglez@gmail.com
License: MIT
Platform: UNKNOWN
Classifier: Development Status :: 3 - Alpha
Classifier: Environment :: Console
Classifier: Intended Audience :: Developers
Classifier: Intended Audience :: Science/Research
Classifier: Intended Audience :: Education
Classifier: Operating System :: MacOS :: MacOS X
Classifier: Operating System :: POSIX :: Linux
Classifier: License :: OSI Approved :: MIT License
Classifier: Programming Language :: Python :: 3.6
Classifier: Programming Language :: Python :: 3.7
Classifier: Programming Language :: Python :: 3.8
Classifier: Topic :: System :: Monitoring
Classifier: Topic :: Scientific/Engineering
Classifier: Topic :: Software Development :: Embedded Systems
Classifier: Topic :: Terminals
Requires-Dist: argcomplete
Requires-Dist: prompt-toolkit
Requires-Dist: requests
Requires-Dist: bleak
Requires-Dist: Pygments
Requires-Dist: netifaces
